url_marshall/__init__.py
url_marshall/url_marshall.py
url_marshall-1.1.0.3.dist-info/METADATA
url_marshall-1.1.0.3.dist-info/WHEEL
url_marshall-1.1.0.3.dist-info/entry_points.txt
url_marshall-1.1.0.3.dist-info/top_level.txt
url_marshall-1.1.0.3.dist-info/RECORD
