Metadata-Version: 2.1
Name: url-marshall
Version: 1.1.0.3
Home-page: https://github.com/mdaseem03/url_marshall
Requires-Dist: argparse
